pygfc.cp310-win32.pyd
pygfc-1.1.0.dist-info/LICENSE
pygfc-1.1.0.dist-info/METADATA
pygfc-1.1.0.dist-info/WHEEL
pygfc-1.1.0.dist-info/top_level.txt
pygfc-1.1.0.dist-info/RECORD
