Metadata-Version: 2.2
Name: pygfc
Version: 1.1.0
Summary: Implementation of a Generalized-Feistel Cipher for generating random permutations.
Home-page: https://github.com/maxmouchet/gfc
Author: Maxime Mouchet
Author-email: max@maxmouchet.com
Classifier: License :: OSI Approved :: MIT License
Classifier: Operating System :: MacOS :: MacOS X
Classifier: Operating System :: POSIX :: Linux
Classifier: Programming Language :: Cython
Classifier: Programming Language :: Python :: 3
Requires-Python: >=3.6
License-File: LICENSE
Dynamic: author
Dynamic: author-email
Dynamic: classifier
Dynamic: description
Dynamic: description-content-type
Dynamic: home-page
Dynamic: requires-python
Dynamic: summary
